{"stats":{"minecraft:killed_by":{"minecraft:zombie":1,"minecraft:player":3},"minecraft:used":{"minecraft:diamond_sword":64,"minecraft:dirt":20,"minecraft:diamond_shovel":216,"minecraft:grass_block":88,"minecraft:ender_pearl":7,"minecraft:cooked_beef":10},"minecraft:picked_up":{"minecraft:diamond_shovel":1,"minecraft:cooked_beef":12,"minecraft:torch":6,"minecraft:wheat_seeds":3,"minecraft:dandelion":1,"minecraft:spruce_slab":1,"minecraft:grass_block":151,"minecraft:dirt":51,"minecraft:ender_pearl":246},"minecraft:killed":{"minecraft:enderman":523},"minecraft:custom":{"minecraft:time_since_rest":19163,"minecraft:open_chest":13,"minecraft:crouch_one_cm":112,"minecraft:play_one_minute":29145,"minecraft:damage_taken":2265,"minecraft:sprint_one_cm":110179,"minecraft:deaths":5,"minecraft:walk_one_cm":62804,"minecraft:sneak_time":95,"minecraft:walk_under_water_one_cm":476,"minecraft:mob_kills":523,"minecraft:jump":1163,"minecraft:damage_dealt":1024,"minecraft:leave_game":5,"minecraft:time_since_death":17261,"minecraft:walk_on_water_one_cm":322,"minecraft:swim_one_cm":6153,"minecraft:fall_one_cm":34687,"minecraft:fly_one_cm":499361},"minecraft:mined":{"minecraft:grass":11,"minecraft:grass_block":200,"minecraft:dirt":36,"minecraft:sweet_berry_bush":2,"minecraft:dandelion":1,"minecraft:oak_leaves":1,"minecraft:torch":2}},"DataVersion":2580}